python_json_log_formatter/__init__.py
python_json_log_formatter/_version.py
python_json_log_formatter/context_filter.py
python_json_log_formatter/py.typed
python_json_log_formatter/python_json_log_formatter.py
python_json_log_formatter-3.7.0.dist-info/LICENSE
python_json_log_formatter-3.7.0.dist-info/METADATA
python_json_log_formatter-3.7.0.dist-info/WHEEL
python_json_log_formatter-3.7.0.dist-info/top_level.txt
python_json_log_formatter-3.7.0.dist-info/RECORD
