Metadata-Version: 2.1
Name: python_json_log_formatter
Version: 3.7.0
Summary: Supplements a default formatter configuration for machine-readable JSON logging and applies it
Author-email: Niels Korschinsky <niels.korschinsky@ibm.com>
Project-URL: Homepage, https://github.com/IBM/python-json-log-formatter
Project-URL: Bug Tracker, https://github.com/IBM/python-json-log-formatter/issues
Classifier: Programming Language :: Python :: 3
Classifier: License :: OSI Approved :: Apache Software License
Classifier: Operating System :: OS Independent
Requires-Python: >=3.9
License-File: LICENSE
